vuln_scanner/__init__.py
vuln_scanner/admin_panel_finder.py
vuln_scanner/api_security_scanner.py
vuln_scanner/broken_auth_scanner.py
vuln_scanner/clickjacking_scanner.py
vuln_scanner/cors_scanner.py
vuln_scanner/directory_traversal_scanner.py
vuln_scanner/file_inclusion_bypass_scanner.py
vuln_scanner/file_upload_scanner.py
vuln_scanner/graphql_security_scanner.py
vuln_scanner/http_methods_scanner.py
vuln_scanner/lfi_scanner.py
vuln_scanner/open_redirect_scanner.py
vuln_scanner/report_generator.py
vuln_scanner/rfi_scanner.py
vuln_scanner/security_headers_scanner.py
vuln_scanner/sensitive_link_scanner.py
vuln_scanner/server_misconfig_scanner.py
vuln_scanner/sql_scanner.py
vuln_scanner/ssl_scanner.py
vuln_scanner/subdomain_scanner.py
vuln_scanner/xss_scanner.py
vuln_scanner-1.0.2.dist-info/LICENSE.txt
vuln_scanner-1.0.2.dist-info/METADATA
vuln_scanner-1.0.2.dist-info/WHEEL
vuln_scanner-1.0.2.dist-info/top_level.txt
vuln_scanner-1.0.2.dist-info/RECORD
