Metadata-Version: 2.1
Name: vuln_scanner
Version: 1.0.2
Summary: مكتبة Python احترافية لاكتشاف وتأمين المواقع من الثغرات الأمنية الشائعة مثل XSS، SQL Injection، LFI، RFI، وإجراء فحوصات متقدمة على الملفات الحساسة، النطاقات الفرعية، إعدادات CORS، SSL/TLS، ورؤوس الأمان، بالإضافة إلى فحص نقاط ضعف المصادقة وإعادة التوجيه المفتوح.
Home-page: https://github.com/AL-MHIB/
Author: ALMHEB
Author-email: appasqw107@gmail.com
Keywords: security scanner xss sql-injection lfi rfi subdomain-scanner
Classifier: Development Status :: 4 - Beta
Classifier: Intended Audience :: Developers
Classifier: Topic :: Security
Classifier: Programming Language :: Python :: 3
Classifier: License :: OSI Approved :: MIT License
Classifier: Operating System :: OS Independent
Requires-Python: >=3.6
License-File: LICENSE.txt
Requires-Dist: requests
Requires-Dist: beautifulsoup4
Requires-Dist: rich
